data/__init__.py
data/calib.pkl
data/df3d_result.pkl
df3d/__init__.py
df3d/cli.py
df3d/config.py
df3d/core.py
df3d/db.py
df3d/gui.py
df3d/logger.py
df3d/os_util.py
df3d/plot_util.py
df3d/procrustes.py
df3d/signal_util.py
df3d/skeleton_fly.py
df3d/video.py
df3d-0.57.dist-info/LICENSE
df3d-0.57.dist-info/METADATA
df3d-0.57.dist-info/WHEEL
df3d-0.57.dist-info/entry_points.txt
df3d-0.57.dist-info/top_level.txt
df3d-0.57.dist-info/RECORD
