Metadata-Version: 2.1
Name: df3d
Version: 0.57
Summary: GUI and 3D pose estimation pipeline for tethered Drosophila.
Home-page: https://github.com/NeLy-EPFL/DeepFly3D
Author: Semih Gunel
Author-email: gunelsemih@gmail.com
License: UNKNOWN
Platform: UNKNOWN
License-File: LICENSE
Requires-Dist: PyQt5
Requires-Dist: sklearn
Requires-Dist: scipy (<=1.2.1)
Requires-Dist: scikit-video
Requires-Dist: scikit-image
Requires-Dist: matplotlib
Requires-Dist: opencv-python (==4.2.0.32)
Requires-Dist: tqdm
Requires-Dist: colorama
Requires-Dist: progress
Requires-Dist: pytorch-lightning
Requires-Dist: torchvision
Requires-Dist: pyba (==0.13)
Requires-Dist: df2d (==0.15)
